erton/__init__.py
erton/audit.py
erton/cli.py
erton/crypto.py
erton/integrity.py
erton/policy.py
erton/runtime_guard.py
erton/sdk.py
erton/service.py
erton/watch.py
erton/analyzers/aim.py
erton/ui/core.py
erton/ui/ctk.py
erton/ui/imgui_stub.py
erton/ui/tk.py
erton-1.0.0.dist-info/licenses/LICENSE
erton-1.0.0.dist-info/METADATA
erton-1.0.0.dist-info/WHEEL
erton-1.0.0.dist-info/entry_points.txt
erton-1.0.0.dist-info/top_level.txt
erton-1.0.0.dist-info/RECORD
